known/__init__.py
known/basic.py
known/fly.py
known/mail.py
known/nbserver.py
known/torcher.py
known/utils.py
known/zero.py
known/pix/__init__.py
known/pix/__main__.py
known-0.0.32.dist-info/licenses/LICENSE
known-0.0.32.dist-info/METADATA
known-0.0.32.dist-info/WHEEL
known-0.0.32.dist-info/top_level.txt
known-0.0.32.dist-info/RECORD
