Metadata-Version: 2.4
Name: known
Version: 0.0.32
Summary: a collection of reusable python code
Home-page: https://github.com/auto-notify-ps/known
Author: Nelson.S
Author-email: mail.nelsonsharma@gmail.com
Classifier: License :: OSI Approved :: MIT License
License-File: LICENSE
Dynamic: author
Dynamic: author-email
Dynamic: classifier
Dynamic: home-page
Dynamic: license-file
Dynamic: summary
